baseline_models/MSS_mask_model.py
baseline_models/__init__.py
baseline_models/backbones/__init__.py
baseline_models/backbones/bs_roformer.py
baseline_models/backbones/demucs4ht.py
baseline_models/backbones/mel_band_roformer.py
baseline_models/backbones/shared.py
baseline_models/backbones/bs_roformer_utils/attend.py
baseline_models/util/other.py
baseline_models/util/registry.py
baseline_models/util/utils.py
bigvgan_utils/__init__.py
bigvgan_utils/activations.py
bigvgan_utils/bigvgan.py
bigvgan_utils/discriminators.py
bigvgan_utils/env.py
bigvgan_utils/inference_e2e.py
bigvgan_utils/loss.py
bigvgan_utils/meldataset.py
bigvgan_utils/train.py
bigvgan_utils/utils.py
bigvgan_utils/alias_free_activation/__init__.py
bigvgan_utils/alias_free_activation/cuda/__init__.py
bigvgan_utils/alias_free_activation/cuda/activation1d.py
bigvgan_utils/alias_free_activation/cuda/load.py
bigvgan_utils/alias_free_activation/torch/__init__.py
bigvgan_utils/alias_free_activation/torch/act.py
bigvgan_utils/alias_free_activation/torch/filter.py
bigvgan_utils/alias_free_activation/torch/resample.py
bigvgan_utils/configs/__init__.py
bigvgan_utils/configs/bigvgan_v2_44khz_128band_512x.json
eval_utils/__init__.py
eval_utils/emb_mse.py
eval_utils/emb_mse_batch.py
eval_utils/model_loader.py
eval_utils/utils.py
gensvs/__init__.py
gensvs/cli.py
gensvs/evaluate.py
gensvs/models.py
gensvs/py.typed
gensvs-2.0.4.dist-info/licenses/LICENSE
sgmsvs/MSS_dataset.py
sgmsvs/MSS_model.py
sgmsvs/__init__.py
sgmsvs/data_module.py
sgmsvs/loudness.py
sgmsvs/sgmse/__init__.py
sgmsvs/sgmse/sdes.py
sgmsvs/sgmse/backbones/__init__.py
sgmsvs/sgmse/backbones/dcunet.py
sgmsvs/sgmse/backbones/ncsnpp.py
sgmsvs/sgmse/backbones/ncsnpp_48k.py
sgmsvs/sgmse/backbones/ncsnpp_v2.py
sgmsvs/sgmse/backbones/shared.py
sgmsvs/sgmse/backbones/ncsnpp_utils/__init__.py
sgmsvs/sgmse/backbones/ncsnpp_utils/layers.py
sgmsvs/sgmse/backbones/ncsnpp_utils/layerspp.py
sgmsvs/sgmse/backbones/ncsnpp_utils/normalization.py
sgmsvs/sgmse/backbones/ncsnpp_utils/up_or_down_sampling.py
gensvs-2.0.4.dist-info/METADATA
gensvs-2.0.4.dist-info/WHEEL
gensvs-2.0.4.dist-info/entry_points.txt
gensvs-2.0.4.dist-info/top_level.txt
gensvs-2.0.4.dist-info/RECORD
