Metadata-Version: 2.4
Name: gensvs
Version: 2.0.4
Summary: Add your description here
Author-email: "Paul A. Bereuter" <paul.bereuter@gmail.com>
License-Expression: MIT
Project-URL: Homepage, https://pablebe.github.io/gensvs_eval_companion_page/
Project-URL: Repository, https://github.com/pablebe/gensvs
Keywords: singing voice separation,muscial source separation,generative models,audio quality assessment
Requires-Python: >=3.13
License-File: LICENSE
Requires-Dist: auraloss>=0.4.0
Requires-Dist: beartype>=0.21.0
Requires-Dist: cmake>=4.0.3
Requires-Dist: demucs>=4.0.1
Requires-Dist: einops>=0.8.1
Requires-Dist: huggingface-hub>=0.23.4
Requires-Dist: hypy-utils>=1.0.29
Requires-Dist: librosa>=0.8.1
Requires-Dist: matplotlib>=3.10.3
Requires-Dist: ml-collections>=1.1.0
Requires-Dist: music2latent>=0.1.6
Requires-Dist: ninja>=1.11.1.4
Requires-Dist: nnaudio>=0.3.3
Requires-Dist: numpy<2
Requires-Dist: omegaconf>=2.3.0
Requires-Dist: openunmix>=1.3.0
Requires-Dist: pesq>=0.0.4
Requires-Dist: ptflops>=0.7.4
Requires-Dist: pytorch-lightning>=2.5.2
Requires-Dist: rotary-embedding-torch>=0.8.8
Requires-Dist: scipy>=1.16.0
Requires-Dist: setuptools>=80.9.0
Requires-Dist: soundfile>=0.13.1
Requires-Dist: tensorboard>=2.20.0
Requires-Dist: torch>=2.7.1
Requires-Dist: torch-ema>=0.3
Requires-Dist: torchaudio>=2.7.1
Requires-Dist: torchmetrics>=1.7.4
Requires-Dist: tqdm>=4.67.1
Requires-Dist: transformers>=4.53.3
Requires-Dist: wandb>=0.21.0
Dynamic: license-file
